Metadata-Version: 1.1
Name: scikit-procrustes
Version: 0.1
Summary: Package of solvers for the Orthogonal Procrustes Problem
Home-page: https://github.com/melissawm/skprocrustes
Author: Melissa Weber Mendonça
Author-email: melissawm@gmail.com
License: BSD
Download-URL: https://github.com/melissawm/skprocrustes
Platform: UNKNOWN
Classifier: Development Status :: 3 - Alpha
Classifier: Intended Audience :: Developers
Classifier: Intended Audience :: Science/Research
Classifier: License :: OSI Approved :: BSD License
Classifier: Topic :: Scientific/Engineering :: Mathematics
